soda_generator/__init__.py
soda_generator/connectors/__init__.py
soda_generator/connectors/click_connect.py
soda_generator/connectors/connection_manager.py
soda_generator/connectors/connectors.py
soda_generator/connectors/trino_connector.py
soda_generator/generators/__init__.py
soda_generator/generators/contract_variable.py
soda_generator/generators/soda_generator.py
soda_generator/profilers/__init__.py
soda_generator/profilers/profiler.py
soda_generator-1100.dist-info/METADATA
soda_generator-1100.dist-info/WHEEL
soda_generator-1100.dist-info/top_level.txt
soda_generator-1100.dist-info/RECORD
