Metadata-Version: 2.1
Name: soda_generator
Version: 1100
Summary: This is package designed for auto-generation of contracts and tests in the soda syntax
Author: Mira Terekhova
Author-email: miraterekhova@mail.ru
Classifier: Programming Language :: Python :: 3
Classifier: License :: OSI Approved :: MIT License
Classifier: Operating System :: OS Independent
Requires-Python: >=3.7
